wagtail_icon_picker/__init__.py
wagtail_icon_picker/blocks.py
wagtail_icon_picker/edit_handlers.py
wagtail_icon_picker/fields.py
wagtail_icon_picker/validators.py
wagtail_icon_picker/widgets.py
wagtail_icon_picker/migrations/__init__.py
wagtail_icon_picker/static/wagtail_icon_picker/iconpicker.js
wagtail_icon_picker/static/wagtail_icon_picker/css/icon-picker-widget.css
wagtail_icon_picker/static/wagtail_icon_picker/css/icofont/icofont.css
wagtail_icon_picker/static/wagtail_icon_picker/css/icofont/icofont.min.css
wagtail_icon_picker/static/wagtail_icon_picker/css/icofont/fonts/icofont.eot
wagtail_icon_picker/static/wagtail_icon_picker/css/icofont/fonts/icofont.svg
wagtail_icon_picker/static/wagtail_icon_picker/css/icofont/fonts/icofont.ttf
wagtail_icon_picker/static/wagtail_icon_picker/css/icofont/fonts/icofont.woff
wagtail_icon_picker/static/wagtail_icon_picker/css/icofont/fonts/icofont.woff2
wagtail_icon_picker/static/wagtail_icon_picker/iconsets/bootstrap5.json
wagtail_icon_picker/static/wagtail_icon_picker/iconsets/boxicons.json
wagtail_icon_picker/static/wagtail_icon_picker/iconsets/fontawesome4.json
wagtail_icon_picker/static/wagtail_icon_picker/iconsets/icofont.json
wagtail_icon_picker/templates/wagtail_icon_picker/widgets/bootstrap-icon-picker-widget.html
wagtail_icon_picker/templates/wagtail_icon_picker/widgets/box-icons-picker-widget.html
wagtail_icon_picker/templates/wagtail_icon_picker/widgets/font-awesome-icon-picker-widget.html
wagtail_icon_picker/templates/wagtail_icon_picker/widgets/icofont-picker-widget.html
wagtail_icon_picker-0.0.8.dist-info/LICENSE
wagtail_icon_picker-0.0.8.dist-info/METADATA
wagtail_icon_picker-0.0.8.dist-info/WHEEL
wagtail_icon_picker-0.0.8.dist-info/top_level.txt
wagtail_icon_picker-0.0.8.dist-info/RECORD
