Metadata-Version: 2.1
Name: wagtail-icon-picker
Version: 0.0.8
Summary: Wagtail CMS icon picker including Bootstrap Icons, Boxicons, Icofont & Font awesome libraries.
Home-page: https://github.com/xeroticikot/wagtail-icon-picker
Author: Mahmud Abdur Rahman
Author-email: clanlord.ikot@gmail.com
License: MIT
Project-URL: Bug Tracker, https://github.com/xeroticikot/wagtail-icon-picker/issues
Platform: UNKNOWN
Classifier: Development Status :: 4 - Beta
Classifier: Environment :: Web Environment
Classifier: Framework :: Django
Classifier: Framework :: Wagtail
Classifier: Framework :: Wagtail :: 2
Classifier: Intended Audience :: Developers
Classifier: License :: OSI Approved :: MIT License
Classifier: Operating System :: OS Independent
Classifier: Programming Language :: Python
Classifier: Programming Language :: Python :: 3
Classifier: Programming Language :: Python :: 3.6
Classifier: Programming Language :: Python :: 3.7
Classifier: Programming Language :: Python :: 3.8
Classifier: Programming Language :: Python :: 3.9
Classifier: Topic :: Utilities
Requires-Python: >=3.6
License-File: LICENSE
Requires-Dist: wagtail
Provides-Extra: test
Requires-Dist: pytest-django ; extra == 'test'
Requires-Dist: wagtail-factories ; extra == 'test'
Requires-Dist: pytest ; extra == 'test'
